<?xml version='1.0' encoding='utf-8'?>

<window xmlns="http://www.w3schools.com"
xmlns:xsi="http://www.w3.org/2001/XMLSchema-instance"
xsi:schemaLocation="http://www.w3schools.com ./ViewConfig.xsd">
    <widget>
        <name>CPULoad</name>
        <attributes>
            <name>CPU#1</name>
        </attributes>
    </widget>
    <widget>
        <name>CPULoad</name>
        <attributes>
            <relx>10</relx>
            <name>CPU#2</name>
        </attributes>
    </widget>
    <widget>
        <name>CPULoad</name>
        <attributes>
            <rely>10</rely>
            <name>CPU#3</name>
        </attributes>
    </widget>
</window>